serendipity_matrix/__init__.py
serendipity_matrix/serendipity_matrix.py
serendipity_matrix-1.0.2.dist-info/licenses/LICENSE
serendipity_matrix-1.0.2.dist-info/METADATA
serendipity_matrix-1.0.2.dist-info/WHEEL
serendipity_matrix-1.0.2.dist-info/top_level.txt
serendipity_matrix-1.0.2.dist-info/RECORD
