Metadata-Version: 2.4
Name: serendipity_matrix
Version: 1.0.2
Summary: Serendipity Matrix
Author: Jesús S. Aguilar-Ruiz, Alejandro García Conde
License: BSD 3-Clause License
License-File: LICENSE
Requires-Dist: numpy
Requires-Dist: pandas
Requires-Dist: matplotlib
Dynamic: author
Dynamic: description
Dynamic: description-content-type
Dynamic: license
Dynamic: license-file
Dynamic: requires-dist
Dynamic: summary
